tests/__init__.py
tests/test_core.py
tests/test_package.py
xlab/__init__.py
xlab/core.py
xlab/jb_utils.py
xlab/models.py
xlab/utils.py
xlab/data/CNN_weights.pth
xlab/data/adversarial_noise.png
xlab/data/cat.jpg
xlab/data/cb_train.json
xlab/tests/__init__.py
xlab/tests/circuit_breakers.py
xlab/tests/cw.py
xlab/tests/distillation.py
xlab/tests/ensemble.py
xlab/tests/gcg.py
xlab/tests/gpt2.py
xlab/tests/msj.py
xlab/tests/pgd.py
xlab/tests/ppl_filters.py
xlab/tests/robustbench.py
xlab/tests/square.py
xlab/tests/visual_jailbreaks.py
xlab/tests/data/cifar10_data.pkl
xlab_security-0.1.13.dist-info/METADATA
xlab_security-0.1.13.dist-info/WHEEL
xlab_security-0.1.13.dist-info/top_level.txt
xlab_security-0.1.13.dist-info/RECORD
